[
   {
      "text": "UK MENTERI PERTANIAN SYAHRUL YASIN LIMPO TERKAIT DUGAAN KORUPSI",
      "start time": 0,
      "end time": 10,
      "duration": -10,
      "repeat": 0
   },
   {
      "text": "KAWAL PEMERATAAN PEMBANGUNAN DI DAERAH OTONOMI BARU PAPUA MAHFUD MD PANGLIMA TNI KAPOLRI HINGGA MENKEU BULAN DEPAN AKAN BERKANTOR",
      "start time": 1,
      "end time": 22,
      "duration": -21,
      "repeat": 0
   },
   {
      "text": "KAPOLRI HINGGA MENKEU BULAN DEPAN AKAN BERKANTOR DI PAPUA",
      "start time": 24,
      "end time": 29,
      "duration": -5,
      "repeat": 0
   }
]